ilsadvbisnvavojebaij/__init__.py
ilsadvbisnvavojebaij/math/__init__.py
ilsadvbisnvavojebaij/math/scalars.py
ilsadvbisnvavojebaij/math/vectors.py
ilsadvbisnvavojebaij/utils/__init__.py
ilsadvbisnvavojebaij/utils/logging.py
ilsadvbisnvavojebaij-0.3.5.dist-info/METADATA
ilsadvbisnvavojebaij-0.3.5.dist-info/WHEEL
ilsadvbisnvavojebaij-0.3.5.dist-info/top_level.txt
ilsadvbisnvavojebaij-0.3.5.dist-info/RECORD
