Metadata-Version: 2.1
Name: ilsadvbisnvavojebaij
Version: 0.3.5
Summary: A randome placeholder package for CI testing
Author: Francisco Castillo
Author-email: fjcastillocarrasco@gmail.com
Classifier: Development Status :: 1 - Planning
Classifier: Intended Audience :: Developers
Classifier: Programming Language :: Python :: 3.10
Classifier: Programming Language :: Python :: 3.11
Classifier: Topic :: Scientific/Engineering :: Artificial Intelligence
Requires-Python: >=3.10
Requires-Dist: numpy (~=1.24.0)
